lexset_dataset_bridge-1.5.1.dist-info/METADATA
lexset_dataset_bridge-1.5.1.dist-info/WHEEL
lexset_dataset_bridge-1.5.1.dist-info/license_files/LICENSE.md
lexset_dataset_bridge-1.5.1.dist-info/license_files/LICENSE.md
lexset_dataset_bridge/__init__.py
lexset_dataset_bridge/lexset_dataset_bridge.cpython-310-x86_64-linux-gnu.so
lexset_dataset_bridge-1.5.1.dist-info/RECORD
